syncnet_python/SyncNetInstance.py
syncnet_python/SyncNetModel.py
syncnet_python/__init__.py
syncnet_python/cli.py
syncnet_python/run_syncnet_pipeline_on_1example.py
syncnet_python/run_syncnet_pipeline_on_mocha_generation_on_mocha_bench.py
syncnet_python/run_syncnet_pipeline_on_your_own_model_results.py
syncnet_python/safe_syncnet_utils.py
syncnet_python/syncnet_pipeline.py
syncnet_python/test_error_handling.py
syncnet_python/test_lse_metrics.py
syncnet_python/detectors/__init__.py
syncnet_python/detectors/s3fd/__init__.py
syncnet_python/detectors/s3fd/box_utils.py
syncnet_python/detectors/s3fd/nets.py
syncnet_python-0.2.2.dist-info/licenses/LICENSE
syncnet_python-0.2.2.dist-info/METADATA
syncnet_python-0.2.2.dist-info/WHEEL
syncnet_python-0.2.2.dist-info/entry_points.txt
syncnet_python-0.2.2.dist-info/top_level.txt
syncnet_python-0.2.2.dist-info/RECORD
