Metadata-Version: 2.4
Name: syncnet-python
Version: 0.2.2
Summary: SyncNet: Audio-visual synchronization detection using deep learning. Updated version of https://github.com/joonson/syncnet_python for modern Python versions.
Author: SyncNet Python Contributors
Maintainer: SyncNet Python Contributors
License: MIT
Project-URL: Homepage, https://github.com/nawta/SyncNet_py313
Project-URL: Bug Reports, https://github.com/nawta/SyncNet_py313/issues
Project-URL: Source, https://github.com/nawta/SyncNet_py313
Keywords: audio-visual,synchronization,deep-learning,pytorch,lip-sync,video-processing,computer-vision
Classifier: Development Status :: 4 - Beta
Classifier: Intended Audience :: Science/Research
Classifier: Intended Audience :: Developers
Classifier: License :: OSI Approved :: MIT License
Classifier: Operating System :: OS Independent
Classifier: Programming Language :: Python :: 3
Classifier: Programming Language :: Python :: 3.9
Classifier: Programming Language :: Python :: 3.10
Classifier: Programming Language :: Python :: 3.11
Classifier: Programming Language :: Python :: 3.12
Classifier: Programming Language :: Python :: 3.13
Classifier: Topic :: Scientific/Engineering :: Artificial Intelligence
Classifier: Topic :: Multimedia :: Video
Classifier: Topic :: Scientific/Engineering :: Image Processing
Requires-Python: >=3.9
License-File: LICENSE
Requires-Dist: torch>=2.0.0
Requires-Dist: torchvision>=0.15.0
Requires-Dist: numpy>=1.24.0
Requires-Dist: scipy>=1.10.0
Requires-Dist: pandas>=2.0.0
Requires-Dist: scenedetect[opencv]>=0.6.0
Requires-Dist: opencv-contrib-python>=4.8.0
Requires-Dist: python-speech-features>=0.6
Requires-Dist: ffmpeg-python>=0.2.0
Provides-Extra: dev
Requires-Dist: pytest>=7.4.0; extra == "dev"
Requires-Dist: pytest-asyncio>=0.21.0; extra == "dev"
Requires-Dist: black>=23.0.0; extra == "dev"
Requires-Dist: ruff>=0.1.0; extra == "dev"
Requires-Dist: mypy>=1.7.0; extra == "dev"
Requires-Dist: types-opencv-python; extra == "dev"
Requires-Dist: types-scipy; extra == "dev"
Dynamic: license-file
